Metadata-Version: 2.4
Name: mcp-text-editor-fastmcp
Version: 0.0.0.dev0
Summary: MCP Text Editor Server - Edit text files via MCP protocol
Project-URL: Homepage, https://github.com/fastmcp-me/mcp-text-editor#readme
Project-URL: Repository, https://github.com/fastmcp-me/mcp-text-editor.git
Project-URL: Issues, https://github.com/fastmcp-me/mcp-text-editor/issues
Author: tumf
License: MIT
License-File: LICENSE
Requires-Python: >=3.13
Requires-Dist: asyncio>=3.4.3
Requires-Dist: chardet>=5.2.0
Requires-Dist: mcp>=1.2.0
Provides-Extra: dev
Requires-Dist: black>=23.3.0; extra == 'dev'
Requires-Dist: isort>=5.12.0; extra == 'dev'
Requires-Dist: mypy>=1.2.0; extra == 'dev'
Requires-Dist: pre-commit>=3.2.2; extra == 'dev'
Requires-Dist: ruff>=0.0.262; extra == 'dev'
Provides-Extra: test
Requires-Dist: pytest-asyncio>=0.24.0; extra == 'test'
Requires-Dist: pytest-cov>=6.0.0; extra == 'test'
Requires-Dist: pytest-env>=1.1.0; extra == 'test'
Requires-Dist: pytest-mock>=3.12.0; extra == 'test'
Requires-Dist: pytest>=8.3.4; extra == 'test'
